README.rst
setup.cfg
setup.py
drf_test_case/__init__.py
drf_test_case/test.py
drf_test_case.egg-info/PKG-INFO
drf_test_case.egg-info/SOURCES.txt
drf_test_case.egg-info/dependency_links.txt
drf_test_case.egg-info/requires.txt
drf_test_case.egg-info/top_level.txt
drf_test_case.egg-info/zip-safe