Metadata-Version: 1.0
Name: drf_test_case
Version: 0.0.1
Summary: using python code to communicate with aws client
Home-page: https://github.com/MrLawes/drf_test_case
Author: Lawes
Author-email: haiou_chen@sina.cn
License: MIT
Platform: UNKNOWN
